ups_landedcost_client/__init__.py
ups_landedcost_client/sdk.py
ups_landedcost_client/hooks/__init__.py
ups_landedcost_client/hooks/hook.py
ups_landedcost_client/models/__init__.py
ups_landedcost_client/models/base.py
ups_landedcost_client/models/brokerage_fee_items.py
ups_landedcost_client/models/errors.py
ups_landedcost_client/models/landed_cost_request.py
ups_landedcost_client/models/landed_cost_request_shipment.py
ups_landedcost_client/models/landed_cost_response.py
ups_landedcost_client/models/request_shipment_items.py
ups_landedcost_client/models/response_shipment_items.py
ups_landedcost_client/models/utils/cast_models.py
ups_landedcost_client/models/utils/json_map.py
ups_landedcost_client/net/__init__.py
ups_landedcost_client/net/environment/__init__.py
ups_landedcost_client/net/environment/environment.py
ups_landedcost_client/net/headers/__init__.py
ups_landedcost_client/net/headers/base_header.py
ups_landedcost_client/net/headers/basic_auth.py
ups_landedcost_client/net/request_chain/__init__.py
ups_landedcost_client/net/request_chain/request_chain.py
ups_landedcost_client/net/request_chain/handlers/__init__.py
ups_landedcost_client/net/request_chain/handlers/base_handler.py
ups_landedcost_client/net/request_chain/handlers/hook_handler.py
ups_landedcost_client/net/request_chain/handlers/http_handler.py
ups_landedcost_client/net/request_chain/handlers/retry_handler.py
ups_landedcost_client/net/transport/__init__.py
ups_landedcost_client/net/transport/request.py
ups_landedcost_client/net/transport/request_error.py
ups_landedcost_client/net/transport/response.py
ups_landedcost_client/net/transport/serializer.py
ups_landedcost_client/net/transport/utils.py
ups_landedcost_client/services/__init__.py
ups_landedcost_client/services/landedcost.py
ups_landedcost_client/services/utils/base_service.py
ups_landedcost_client/services/utils/default_headers.py
ups_landedcost_client/services/utils/validator.py
ups_landedcost_client-1.0.1.dist-info/LICENSE
ups_landedcost_client-1.0.1.dist-info/METADATA
ups_landedcost_client-1.0.1.dist-info/WHEEL
ups_landedcost_client-1.0.1.dist-info/top_level.txt
ups_landedcost_client-1.0.1.dist-info/RECORD
