Metadata-Version: 2.1
Name: ups-landedcost-client
Version: 1.0.1
Summary: The Landed Cost Quote API allows you to estimate the all-inclusive cost of international shipments
License: MIT
Requires-Python: >=3.7
License-File: LICENSE
Requires-Dist: requests >=2.31.0
